keystone_oidc_auth_plugin/__init__.py
keystone_oidc_auth_plugin/auth.py
keystone_oidc_auth_plugin/configuration.py
keystone_oidc_auth_plugin/opts.py
keystone_oidc_auth_plugin/tests/__init__.py
keystone_oidc_auth_plugin/tests/base.py
keystone_oidc_auth_plugin/tests/test_keystone_oidc_auth_plugin.py
keystone_oidc_auth_plugin-1.0.0.dist-info/AUTHORS
keystone_oidc_auth_plugin-1.0.0.dist-info/LICENSE
keystone_oidc_auth_plugin-1.0.0.dist-info/METADATA
keystone_oidc_auth_plugin-1.0.0.dist-info/WHEEL
keystone_oidc_auth_plugin-1.0.0.dist-info/entry_points.txt
keystone_oidc_auth_plugin-1.0.0.dist-info/pbr.json
keystone_oidc_auth_plugin-1.0.0.dist-info/top_level.txt
keystone_oidc_auth_plugin-1.0.0.dist-info/RECORD
