Metadata-Version: 2.1
Name: keystone-oidc-auth-plugin
Version: 1.0.0
Summary: OpenID Connect Implementation for OpenStack Keystone.
Home-page: http://www.ifca.es/
Author: Spanish National Research Council
Author-email: computing@ifca.unican.es
License: UNKNOWN
Platform: UNKNOWN
Classifier: Environment :: OpenStack
Classifier: Intended Audience :: Information Technology
Classifier: Intended Audience :: System Administrators
Classifier: License :: OSI Approved :: Apache Software License
Classifier: Operating System :: POSIX :: Linux
Classifier: Programming Language :: Python
Classifier: Programming Language :: Python :: 2
Classifier: Programming Language :: Python :: 2.7
Classifier: Programming Language :: Python :: 3
Classifier: Programming Language :: Python :: 3.6
Requires-Dist: pbr (>=2.0)
Requires-Dist: oic (>=0.15.1)
Requires-Dist: pyjwkest (>=1.4.2)
